setup.py
euclid_wfm/__init__.py
euclid_wfm/test.py
euclid_wfm.egg-info/PKG-INFO
euclid_wfm.egg-info/SOURCES.txt
euclid_wfm.egg-info/dependency_links.txt
euclid_wfm.egg-info/requires.txt
euclid_wfm.egg-info/top_level.txt
euclid_wfm/bin/__init__.py
euclid_wfm/bin/client_for_test.py
euclid_wfm/bin/pipeline_runner.py
euclid_wfm/bin/pipeline_server_flask.py
euclid_wfm/euclidwf/__init__.py
euclid_wfm/euclidwf/framework/__init__.py
euclid_wfm/euclidwf/framework/configuration.py
euclid_wfm/euclidwf/framework/context.py
euclid_wfm/euclidwf/framework/drm_access.py
euclid_wfm/euclidwf/framework/graph_builder.py
euclid_wfm/euclidwf/framework/graph_tasks.py
euclid_wfm/euclidwf/framework/node_callbacks.py
euclid_wfm/euclidwf/framework/runner.py
euclid_wfm/euclidwf/framework/taskdefs.py
euclid_wfm/euclidwf/framework/taskprops.py
euclid_wfm/euclidwf/framework/workflow_dsl.py
euclid_wfm/euclidwf/framework/tests/__init__.py
euclid_wfm/euclidwf/framework/tests/pipeline_for_test.py
euclid_wfm/euclidwf/framework/tests/test_graph_builder.py
euclid_wfm/euclidwf/framework/tests/test_graph_tasks.py
euclid_wfm/euclidwf/framework/tests/test_node_callbacks.py
euclid_wfm/euclidwf/framework/tests/test_runner.py
euclid_wfm/euclidwf/framework/tests/test_workflow_dsl.py
euclid_wfm/euclidwf/generators/__init__.py
euclid_wfm/euclidwf/generators/exec_stubs_generator.py
euclid_wfm/euclidwf/generators/mock_data_generator.py
euclid_wfm/euclidwf/generators/proxy_functions_generator.py
euclid_wfm/euclidwf/server/__init__.py
euclid_wfm/euclidwf/server/server_config.py
euclid_wfm/euclidwf/server/server_model.py
euclid_wfm/euclidwf/server/server_views_flask.py
euclid_wfm/euclidwf/utilities/__init__.py
euclid_wfm/euclidwf/utilities/cmd_executor.py
euclid_wfm/euclidwf/utilities/config_loader.py
euclid_wfm/euclidwf/utilities/data_loader.py
euclid_wfm/euclidwf/utilities/error_handling.py
euclid_wfm/euclidwf/utilities/exec_loader.py
euclid_wfm/euclidwf/utilities/file_transporter.py
euclid_wfm/euclidwf/utilities/thread_local.py
euclid_wfm/euclidwf/utilities/utils.py
euclid_wfm/euclidwf/utilities/visualizer.py