Metadata-Version: 1.0
Name: euclid-wfm
Version: 0.4.4
Summary: Euclid pipeline framework
Home-page: UNKNOWN
Author: Martin Melchior
Author-email: martin.melchior@fhnw.ch
License: UNKNOWN
Platform: UNKNOWN
